[
  {
    "id": "1",
    "name": "Маргарита",
    "last_name": "Булацкая",
    "history": "Рита родилась в срок и была почти абсолютно здоровым ребёнком. Почему почти? Потому что единственным врачем, который поставил диагноз, был невролог. Диагноз был нестрашный, часто ставился деткам при рождений и требовал минимального лечения.\r\nНо время шло и Нина (мама Риты) стала все чаще и чаще замечать особенности у своего ребёнка. Рита не заговорила в 2-а годика, потом и к 3-м и к 4-с годам продолжала молчать. Все это время мама с Ритой ходила по больницам и просила разобраться, но получала одни и те же ответы: «Успокойтесь, это особенности развития. Заговорит».\r\nЛишь только к 5-и годам стало ясно, что это не особенности развития и у Риты что-то намного более серьезное. Врачами был поставлен страшный диагноз-неспецифический аутизм. Помимо него в медицинской карте Риты появилось ещё 4 диагноза, в том числе и поломка генов.\r\nРодители собирают деньги на реабилитацию и последующую социализацию дочки, а также ищут специалистов в детской неврологии и генетике, которые бы смогли помочь в дальнейшей диагностики и выборе тактики лечения многочисленных проблем.",
    "sum1": "45",
    "sum2": "444100",
    "avatar": "img/avatars/margorita.png",
    "status": "active",
    "photo": "img/help/margorita.png"
  },
  {
    "id": "8",
    "name": "Aртур",
    "last_name": "Тестовый",
    "history": "История ребенка...",
    "sum1": "1",
    "sum2": "20",
    "avatar": "img/avatars/avatar-6135d035475e6.jpg",
    "status": "finished",
    "photo": "img/help/artur.png"
  },
  {
    "id": "9",
    "name": "ioasjfoiafj",
    "last_name": "jfaijfoiasjfopiajfs",
    "history": "История ребенка...",
    "sum1": "1",
    "sum2": "123",
    "avatar": "img/avatars/avatar-6135d035475e6.jpg",
    "status": "active",
    "photo": "img/help/artur.png"
  }
]
